aws_lambda_event_types/__init__.py
aws_lambda_event_types/exceptions.py
aws_lambda_event_types/sns.py
python_aws_lambda_event_types-0.0.3.dist-info/LICENSE
python_aws_lambda_event_types-0.0.3.dist-info/METADATA
python_aws_lambda_event_types-0.0.3.dist-info/WHEEL
python_aws_lambda_event_types-0.0.3.dist-info/RECORD
